Metadata-Version: 2.1
Name: EasyPhenology
Version: 0.0.1
Summary: Calculates vegetation phenological transition dates
Home-page: UNKNOWN
Author: Annu Panwar
Author-email: apanwar@bgc-jena.mpg.de
License: MIT
Keywords: Phenology
Platform: UNKNOWN
Classifier: Development Status :: 5 - Production/Stable
Classifier: Intended Audience :: Education
Classifier: Operating System :: Microsoft :: Windows :: Windows 10
Classifier: License :: OSI Approved :: MIT License
Classifier: Programming Language :: Python :: 3
